amulety/__init__.py
amulety/__main__.py
amulety/amulety.py
amulety/bcr_embeddings.py
amulety/protein_embeddings.py
amulety/tcr_embeddings.py
amulety/utils.py
amulety-2.1.2.dist-info/licenses/LICENSE
amulety-2.1.2.dist-info/METADATA
amulety-2.1.2.dist-info/WHEEL
amulety-2.1.2.dist-info/entry_points.txt
amulety-2.1.2.dist-info/top_level.txt
amulety-2.1.2.dist-info/RECORD
