Metadata-Version: 2.4
Name: amulety
Version: 2.1.2
Summary: Python package to create embeddings of BCR amino acid sequences.
Author-email: Mamie Wang <mamie.wang@yale.edu>, Wengyao Jiang <wengyao.jiang@yale.edu>, Steven Kleinstein <steven.kleinstein@yale.edu>, Gisela Gabernet <gisela.gabernet@yale.edu>
License: MIT
Project-URL: Homepage, https://github.com/immcantation/amulety
Project-URL: Repository, https://github.com/immcantation/amulety
Project-URL: Issues, https://github.com/immcantation/amulety/issues
Keywords: immcantation,immunoinformatics,bioinformatics,embedding,antibody,BCR,Machine Learning,biology,NGS,next generation sequencing
Classifier: Development Status :: 4 - Beta
Classifier: Intended Audience :: Science/Research
Classifier: License :: OSI Approved :: MIT License
Classifier: Operating System :: OS Independent
Classifier: Programming Language :: Python :: 3
Classifier: Programming Language :: Python :: 3.8
Classifier: Programming Language :: Python :: 3.9
Classifier: Programming Language :: Python :: 3.10
Classifier: Programming Language :: Python :: 3.11
Classifier: Programming Language :: Python :: 3.12
Classifier: Topic :: Scientific/Engineering :: Bio-Informatics
Requires-Python: <4,>=3.8
License-File: LICENSE
Requires-Dist: numpy
Requires-Dist: pandas
Requires-Dist: torch
Requires-Dist: transformers
Requires-Dist: typer
Requires-Dist: antiberty
Requires-Dist: ablang; python_version < "3.14"
Requires-Dist: rjieba
Requires-Dist: sentencepiece
Requires-Dist: anndata
Dynamic: license-file
